{
	"tile_size": 24,
	"map_width": 25,
	"map_height": 19,
	"layers": [
		{
			"name": "Layer 1", 
			"positions": [
				{ "x":0, "y":0, "id":0 },
				{ "x":0, "y":1, "id":0 },
				{ "x":0, "y":2, "id":0 },
				{ "x":0, "y":3, "id":1 },
				{ "x":0, "y":4, "id":2 },
				{ "x":0, "y":5, "id":3 },
				{ "x":0, "y":6, "id":4 },
				{ "x":0, "y":7, "id":5 },
				{ "x":0, "y":8, "id":6 },
				{ "x":0, "y":9, "id":7 },
				{ "x":0, "y":10, "id":8 },
				{ "x":0, "y":11, "id":9 },
				{ "x":0, "y":12, "id":10 },
				{ "x":0, "y":13, "id":11 },
				{ "x":0, "y":14, "id":12 },
				{ "x":0, "y":15, "id":13 },
				{ "x":0, "y":16, "id":14 },
				{ "x":0, "y":17, "id":15 },
				{ "x":0, "y":18, "id":16 },
				{ "x":1, "y":0, "id":0 },
				{ "x":1, "y":1, "id":0 },
				{ "x":1, "y":2, "id":0 },
				{ "x":1, "y":3, "id":1 },
				{ "x":1, "y":4, "id":2 },
				{ "x":1, "y":5, "id":3 },
				{ "x":1, "y":6, "id":4 },
				{ "x":1, "y":7, "id":5 },
				{ "x":1, "y":8, "id":6 },
				{ "x":1, "y":9, "id":7 },
				{ "x":1, "y":10, "id":8 },
				{ "x":1, "y":11, "id":9 },
				{ "x":1, "y":12, "id":10 },
				{ "x":1, "y":13, "id":11 },
				{ "x":1, "y":14, "id":12 },
				{ "x":1, "y":15, "id":13 },
				{ "x":1, "y":16, "id":14 },
				{ "x":1, "y":17, "id":15 },
				{ "x":1, "y":18, "id":16 },
				{ "x":2, "y":0, "id":0 },
				{ "x":2, "y":1, "id":0 },
				{ "x":2, "y":2, "id":0 },
				{ "x":2, "y":3, "id":1 },
				{ "x":2, "y":4, "id":2 },
				{ "x":2, "y":5, "id":3 },
				{ "x":2, "y":6, "id":4 },
				{ "x":2, "y":7, "id":5 },
				{ "x":2, "y":8, "id":6 },
				{ "x":2, "y":9, "id":7 },
				{ "x":2, "y":10, "id":8 },
				{ "x":2, "y":11, "id":9 },
				{ "x":2, "y":12, "id":10 },
				{ "x":2, "y":13, "id":11 },
				{ "x":2, "y":14, "id":12 },
				{ "x":2, "y":15, "id":13 },
				{ "x":2, "y":16, "id":14 },
				{ "x":2, "y":17, "id":15 },
				{ "x":2, "y":18, "id":16 },
				{ "x":3, "y":0, "id":17 },
				{ "x":3, "y":1, "id":17 },
				{ "x":3, "y":2, "id":17 },
				{ "x":3, "y":3, "id":18 },
				{ "x":3, "y":4, "id":19 },
				{ "x":3, "y":5, "id":20 },
				{ "x":3, "y":6, "id":21 },
				{ "x":3, "y":7, "id":22 },
				{ "x":3, "y":8, "id":23 },
				{ "x":3, "y":9, "id":24 },
				{ "x":3, "y":10, "id":25 },
				{ "x":3, "y":11, "id":26 },
				{ "x":3, "y":12, "id":27 },
				{ "x":3, "y":13, "id":28 },
				{ "x":3, "y":14, "id":29 },
				{ "x":3, "y":15, "id":30 },
				{ "x":3, "y":16, "id":31 },
				{ "x":3, "y":17, "id":32 },
				{ "x":3, "y":18, "id":33 },
				{ "x":4, "y":0, "id":34 },
				{ "x":4, "y":1, "id":34 },
				{ "x":4, "y":2, "id":34 },
				{ "x":4, "y":3, "id":35 },
				{ "x":4, "y":4, "id":36 },
				{ "x":4, "y":5, "id":37 },
				{ "x":4, "y":6, "id":38 },
				{ "x":4, "y":7, "id":39 },
				{ "x":4, "y":8, "id":40 },
				{ "x":4, "y":9, "id":41 },
				{ "x":4, "y":10, "id":42 },
				{ "x":4, "y":11, "id":43 },
				{ "x":4, "y":12, "id":44 },
				{ "x":4, "y":13, "id":45 },
				{ "x":4, "y":14, "id":46 },
				{ "x":4, "y":15, "id":47 },
				{ "x":4, "y":16, "id":48 },
				{ "x":4, "y":17, "id":49 },
				{ "x":4, "y":18, "id":50 },
				{ "x":5, "y":0, "id":51 },
				{ "x":5, "y":1, "id":51 },
				{ "x":5, "y":2, "id":51 },
				{ "x":5, "y":3, "id":52 },
				{ "x":5, "y":4, "id":53 },
				{ "x":5, "y":5, "id":54 },
				{ "x":5, "y":6, "id":55 },
				{ "x":5, "y":7, "id":56 },
				{ "x":5, "y":8, "id":57 },
				{ "x":5, "y":9, "id":58 },
				{ "x":5, "y":10, "id":59 },
				{ "x":5, "y":11, "id":60 },
				{ "x":5, "y":12, "id":61 },
				{ "x":5, "y":13, "id":62 },
				{ "x":5, "y":14, "id":63 },
				{ "x":5, "y":15, "id":64 },
				{ "x":5, "y":16, "id":65 },
				{ "x":5, "y":17, "id":66 },
				{ "x":5, "y":18, "id":67 },
				{ "x":6, "y":0, "id":68 },
				{ "x":6, "y":1, "id":68 },
				{ "x":6, "y":2, "id":68 },
				{ "x":6, "y":3, "id":69 },
				{ "x":6, "y":4, "id":70 },
				{ "x":6, "y":5, "id":71 },
				{ "x":6, "y":6, "id":72 },
				{ "x":6, "y":7, "id":73 },
				{ "x":6, "y":8, "id":74 },
				{ "x":6, "y":9, "id":75 },
				{ "x":6, "y":10, "id":76 },
				{ "x":6, "y":11, "id":77 },
				{ "x":6, "y":12, "id":78 },
				{ "x":6, "y":13, "id":79 },
				{ "x":6, "y":14, "id":80 },
				{ "x":6, "y":15, "id":81 },
				{ "x":6, "y":16, "id":82 },
				{ "x":6, "y":17, "id":83 },
				{ "x":6, "y":18, "id":84 },
				{ "x":7, "y":0, "id":85 },
				{ "x":7, "y":1, "id":85 },
				{ "x":7, "y":2, "id":85 },
				{ "x":7, "y":3, "id":86 },
				{ "x":7, "y":4, "id":87 },
				{ "x":7, "y":5, "id":88 },
				{ "x":7, "y":6, "id":89 },
				{ "x":7, "y":7, "id":90 },
				{ "x":7, "y":8, "id":91 },
				{ "x":7, "y":9, "id":92 },
				{ "x":7, "y":10, "id":93 },
				{ "x":7, "y":11, "id":94 },
				{ "x":7, "y":12, "id":95 },
				{ "x":7, "y":13, "id":96 },
				{ "x":7, "y":14, "id":97 },
				{ "x":7, "y":15, "id":98 },
				{ "x":7, "y":16, "id":99 },
				{ "x":7, "y":17, "id":100 },
				{ "x":7, "y":18, "id":101 },
				{ "x":8, "y":0, "id":102 },
				{ "x":8, "y":1, "id":102 },
				{ "x":8, "y":2, "id":102 },
				{ "x":8, "y":3, "id":103 },
				{ "x":8, "y":4, "id":104 },
				{ "x":8, "y":5, "id":105 },
				{ "x":8, "y":6, "id":106 },
				{ "x":8, "y":7, "id":107 },
				{ "x":8, "y":8, "id":108 },
				{ "x":8, "y":9, "id":109 },
				{ "x":8, "y":10, "id":110 },
				{ "x":8, "y":11, "id":111 },
				{ "x":8, "y":12, "id":112 },
				{ "x":8, "y":13, "id":113 },
				{ "x":8, "y":14, "id":114 },
				{ "x":8, "y":15, "id":115 },
				{ "x":8, "y":16, "id":116 },
				{ "x":8, "y":17, "id":117 },
				{ "x":8, "y":18, "id":118 },
				{ "x":9, "y":0, "id":119 },
				{ "x":9, "y":1, "id":119 },
				{ "x":9, "y":2, "id":119 },
				{ "x":9, "y":3, "id":120 },
				{ "x":9, "y":4, "id":121 },
				{ "x":9, "y":5, "id":122 },
				{ "x":9, "y":6, "id":123 },
				{ "x":9, "y":7, "id":124 },
				{ "x":9, "y":8, "id":125 },
				{ "x":9, "y":9, "id":126 },
				{ "x":9, "y":10, "id":127 },
				{ "x":9, "y":11, "id":128 },
				{ "x":9, "y":12, "id":129 },
				{ "x":9, "y":13, "id":130 },
				{ "x":9, "y":14, "id":131 },
				{ "x":9, "y":15, "id":132 },
				{ "x":9, "y":16, "id":133 },
				{ "x":9, "y":17, "id":134 },
				{ "x":9, "y":18, "id":135 },
				{ "x":10, "y":0, "id":136 },
				{ "x":10, "y":1, "id":136 },
				{ "x":10, "y":2, "id":136 },
				{ "x":10, "y":3, "id":137 },
				{ "x":10, "y":4, "id":138 },
				{ "x":10, "y":5, "id":139 },
				{ "x":10, "y":6, "id":140 },
				{ "x":10, "y":7, "id":141 },
				{ "x":10, "y":8, "id":142 },
				{ "x":10, "y":9, "id":143 },
				{ "x":10, "y":10, "id":144 },
				{ "x":10, "y":11, "id":145 },
				{ "x":10, "y":12, "id":146 },
				{ "x":10, "y":13, "id":147 },
				{ "x":10, "y":14, "id":148 },
				{ "x":10, "y":15, "id":149 },
				{ "x":10, "y":16, "id":150 },
				{ "x":10, "y":17, "id":151 },
				{ "x":10, "y":18, "id":152 },
				{ "x":11, "y":0, "id":153 },
				{ "x":11, "y":1, "id":153 },
				{ "x":11, "y":2, "id":153 },
				{ "x":11, "y":3, "id":154 },
				{ "x":11, "y":4, "id":155 },
				{ "x":11, "y":5, "id":156 },
				{ "x":11, "y":6, "id":157 },
				{ "x":11, "y":7, "id":158 },
				{ "x":11, "y":8, "id":159 },
				{ "x":11, "y":9, "id":160 },
				{ "x":11, "y":10, "id":161 },
				{ "x":11, "y":11, "id":162 },
				{ "x":11, "y":12, "id":163 },
				{ "x":11, "y":13, "id":164 },
				{ "x":11, "y":14, "id":165 },
				{ "x":11, "y":15, "id":166 },
				{ "x":11, "y":16, "id":167 },
				{ "x":11, "y":17, "id":168 },
				{ "x":11, "y":18, "id":169 },
				{ "x":12, "y":0, "id":170 },
				{ "x":12, "y":1, "id":170 },
				{ "x":12, "y":2, "id":170 },
				{ "x":12, "y":3, "id":171 },
				{ "x":12, "y":4, "id":172 },
				{ "x":12, "y":5, "id":173 },
				{ "x":12, "y":6, "id":174 },
				{ "x":12, "y":7, "id":175 },
				{ "x":12, "y":8, "id":176 },
				{ "x":12, "y":9, "id":177 },
				{ "x":12, "y":10, "id":178 },
				{ "x":12, "y":11, "id":179 },
				{ "x":12, "y":12, "id":180 },
				{ "x":12, "y":13, "id":181 },
				{ "x":12, "y":14, "id":182 },
				{ "x":12, "y":15, "id":183 },
				{ "x":12, "y":16, "id":184 },
				{ "x":12, "y":17, "id":185 },
				{ "x":12, "y":18, "id":186 },
				{ "x":13, "y":0, "id":187 },
				{ "x":13, "y":1, "id":187 },
				{ "x":13, "y":2, "id":187 },
				{ "x":13, "y":3, "id":188 },
				{ "x":13, "y":4, "id":189 },
				{ "x":13, "y":5, "id":190 },
				{ "x":13, "y":6, "id":191 },
				{ "x":13, "y":7, "id":192 },
				{ "x":13, "y":8, "id":193 },
				{ "x":13, "y":9, "id":194 },
				{ "x":13, "y":10, "id":195 },
				{ "x":13, "y":11, "id":196 },
				{ "x":13, "y":12, "id":197 },
				{ "x":13, "y":13, "id":198 },
				{ "x":13, "y":14, "id":199 },
				{ "x":13, "y":15, "id":200 },
				{ "x":13, "y":16, "id":201 },
				{ "x":13, "y":17, "id":202 },
				{ "x":13, "y":18, "id":203 },
				{ "x":14, "y":0, "id":204 },
				{ "x":14, "y":1, "id":204 },
				{ "x":14, "y":2, "id":204 },
				{ "x":14, "y":3, "id":205 },
				{ "x":14, "y":4, "id":206 },
				{ "x":14, "y":5, "id":207 },
				{ "x":14, "y":6, "id":208 },
				{ "x":14, "y":7, "id":209 },
				{ "x":14, "y":8, "id":210 },
				{ "x":14, "y":9, "id":211 },
				{ "x":14, "y":10, "id":212 },
				{ "x":14, "y":11, "id":213 },
				{ "x":14, "y":12, "id":214 },
				{ "x":14, "y":13, "id":215 },
				{ "x":14, "y":14, "id":216 },
				{ "x":14, "y":15, "id":217 },
				{ "x":14, "y":16, "id":218 },
				{ "x":14, "y":17, "id":219 },
				{ "x":14, "y":18, "id":220 },
				{ "x":15, "y":0, "id":221 },
				{ "x":15, "y":1, "id":221 },
				{ "x":15, "y":2, "id":221 },
				{ "x":15, "y":3, "id":222 },
				{ "x":15, "y":4, "id":223 },
				{ "x":15, "y":5, "id":224 },
				{ "x":15, "y":6, "id":225 },
				{ "x":15, "y":7, "id":226 },
				{ "x":15, "y":8, "id":227 },
				{ "x":15, "y":9, "id":228 },
				{ "x":15, "y":10, "id":229 },
				{ "x":15, "y":11, "id":230 },
				{ "x":15, "y":12, "id":231 },
				{ "x":15, "y":13, "id":232 },
				{ "x":15, "y":14, "id":233 },
				{ "x":15, "y":15, "id":234 },
				{ "x":15, "y":16, "id":235 },
				{ "x":15, "y":17, "id":236 },
				{ "x":15, "y":18, "id":237 },
				{ "x":16, "y":0, "id":238 },
				{ "x":16, "y":1, "id":238 },
				{ "x":16, "y":2, "id":238 },
				{ "x":16, "y":3, "id":239 },
				{ "x":16, "y":4, "id":240 },
				{ "x":16, "y":5, "id":241 },
				{ "x":16, "y":6, "id":242 },
				{ "x":16, "y":7, "id":243 },
				{ "x":16, "y":8, "id":244 },
				{ "x":16, "y":9, "id":245 },
				{ "x":16, "y":10, "id":246 },
				{ "x":16, "y":11, "id":247 },
				{ "x":16, "y":12, "id":248 },
				{ "x":16, "y":13, "id":249 },
				{ "x":16, "y":14, "id":250 },
				{ "x":16, "y":15, "id":251 },
				{ "x":16, "y":16, "id":252 },
				{ "x":16, "y":17, "id":253 },
				{ "x":16, "y":18, "id":254 },
				{ "x":17, "y":0, "id":255 },
				{ "x":17, "y":1, "id":255 },
				{ "x":17, "y":2, "id":255 },
				{ "x":17, "y":3, "id":256 },
				{ "x":17, "y":4, "id":257 },
				{ "x":17, "y":5, "id":258 },
				{ "x":17, "y":6, "id":259 },
				{ "x":17, "y":7, "id":260 },
				{ "x":17, "y":8, "id":261 },
				{ "x":17, "y":9, "id":262 },
				{ "x":17, "y":10, "id":263 },
				{ "x":17, "y":11, "id":264 },
				{ "x":17, "y":12, "id":265 },
				{ "x":17, "y":13, "id":266 },
				{ "x":17, "y":14, "id":267 },
				{ "x":17, "y":15, "id":268 },
				{ "x":17, "y":16, "id":269 },
				{ "x":17, "y":17, "id":270 },
				{ "x":17, "y":18, "id":271 },
				{ "x":18, "y":0, "id":272 },
				{ "x":18, "y":1, "id":272 },
				{ "x":18, "y":2, "id":272 },
				{ "x":18, "y":3, "id":273 },
				{ "x":18, "y":4, "id":274 },
				{ "x":18, "y":5, "id":275 },
				{ "x":18, "y":6, "id":276 },
				{ "x":18, "y":7, "id":277 },
				{ "x":18, "y":8, "id":278 },
				{ "x":18, "y":9, "id":279 },
				{ "x":18, "y":10, "id":280 },
				{ "x":18, "y":11, "id":281 },
				{ "x":18, "y":12, "id":282 },
				{ "x":18, "y":13, "id":283 },
				{ "x":18, "y":14, "id":284 },
				{ "x":18, "y":15, "id":285 },
				{ "x":18, "y":16, "id":286 },
				{ "x":18, "y":17, "id":287 },
				{ "x":18, "y":18, "id":288 },
				{ "x":19, "y":0, "id":289 },
				{ "x":19, "y":1, "id":289 },
				{ "x":19, "y":2, "id":289 },
				{ "x":19, "y":3, "id":290 },
				{ "x":19, "y":4, "id":291 },
				{ "x":19, "y":5, "id":292 },
				{ "x":19, "y":6, "id":293 },
				{ "x":19, "y":7, "id":294 },
				{ "x":19, "y":8, "id":295 },
				{ "x":19, "y":9, "id":296 },
				{ "x":19, "y":10, "id":297 },
				{ "x":19, "y":11, "id":298 },
				{ "x":19, "y":12, "id":299 },
				{ "x":19, "y":13, "id":300 },
				{ "x":19, "y":14, "id":301 },
				{ "x":19, "y":15, "id":302 },
				{ "x":19, "y":16, "id":303 },
				{ "x":19, "y":17, "id":304 },
				{ "x":19, "y":18, "id":305 },
				{ "x":20, "y":0, "id":306 },
				{ "x":20, "y":1, "id":306 },
				{ "x":20, "y":2, "id":306 },
				{ "x":20, "y":3, "id":307 },
				{ "x":20, "y":4, "id":308 },
				{ "x":20, "y":5, "id":309 },
				{ "x":20, "y":6, "id":310 },
				{ "x":20, "y":7, "id":311 },
				{ "x":20, "y":8, "id":312 },
				{ "x":20, "y":9, "id":313 },
				{ "x":20, "y":10, "id":314 },
				{ "x":20, "y":11, "id":315 },
				{ "x":20, "y":12, "id":316 },
				{ "x":20, "y":13, "id":317 },
				{ "x":20, "y":14, "id":318 },
				{ "x":20, "y":15, "id":319 },
				{ "x":20, "y":16, "id":320 },
				{ "x":20, "y":17, "id":321 },
				{ "x":20, "y":18, "id":322 },
				{ "x":21, "y":0, "id":323 },
				{ "x":21, "y":1, "id":323 },
				{ "x":21, "y":2, "id":323 },
				{ "x":21, "y":3, "id":324 },
				{ "x":21, "y":4, "id":325 },
				{ "x":21, "y":5, "id":326 },
				{ "x":21, "y":6, "id":327 },
				{ "x":21, "y":7, "id":328 },
				{ "x":21, "y":8, "id":329 },
				{ "x":21, "y":9, "id":330 },
				{ "x":21, "y":10, "id":331 },
				{ "x":21, "y":11, "id":332 },
				{ "x":21, "y":12, "id":333 },
				{ "x":21, "y":13, "id":334 },
				{ "x":21, "y":14, "id":335 },
				{ "x":21, "y":15, "id":336 },
				{ "x":21, "y":16, "id":337 },
				{ "x":21, "y":17, "id":338 },
				{ "x":21, "y":18, "id":339 },
				{ "x":22, "y":0, "id":340 },
				{ "x":22, "y":1, "id":340 },
				{ "x":22, "y":2, "id":340 },
				{ "x":22, "y":3, "id":341 },
				{ "x":22, "y":4, "id":342 },
				{ "x":22, "y":5, "id":343 },
				{ "x":22, "y":6, "id":344 },
				{ "x":22, "y":7, "id":345 },
				{ "x":22, "y":8, "id":346 },
				{ "x":22, "y":9, "id":347 },
				{ "x":22, "y":10, "id":348 },
				{ "x":22, "y":11, "id":349 },
				{ "x":22, "y":12, "id":350 },
				{ "x":22, "y":13, "id":351 },
				{ "x":22, "y":14, "id":352 },
				{ "x":22, "y":15, "id":353 },
				{ "x":22, "y":16, "id":354 },
				{ "x":22, "y":17, "id":355 },
				{ "x":22, "y":18, "id":356 },
				{ "x":23, "y":0, "id":0 },
				{ "x":23, "y":1, "id":0 },
				{ "x":23, "y":2, "id":0 },
				{ "x":23, "y":3, "id":1 },
				{ "x":23, "y":4, "id":2 },
				{ "x":23, "y":5, "id":3 },
				{ "x":23, "y":6, "id":4 },
				{ "x":23, "y":7, "id":5 },
				{ "x":23, "y":8, "id":6 },
				{ "x":23, "y":9, "id":7 },
				{ "x":23, "y":10, "id":8 },
				{ "x":23, "y":11, "id":9 },
				{ "x":23, "y":12, "id":10 },
				{ "x":23, "y":13, "id":11 },
				{ "x":23, "y":14, "id":12 },
				{ "x":23, "y":15, "id":13 },
				{ "x":23, "y":16, "id":14 },
				{ "x":23, "y":17, "id":15 },
				{ "x":23, "y":18, "id":16 },
				{ "x":24, "y":0, "id":0 },
				{ "x":24, "y":1, "id":0 },
				{ "x":24, "y":2, "id":0 },
				{ "x":24, "y":3, "id":1 },
				{ "x":24, "y":4, "id":2 },
				{ "x":24, "y":5, "id":3 },
				{ "x":24, "y":6, "id":4 },
				{ "x":24, "y":7, "id":5 },
				{ "x":24, "y":8, "id":6 },
				{ "x":24, "y":9, "id":7 },
				{ "x":24, "y":10, "id":8 },
				{ "x":24, "y":11, "id":9 },
				{ "x":24, "y":12, "id":10 },
				{ "x":24, "y":13, "id":11 },
				{ "x":24, "y":14, "id":12 },
				{ "x":24, "y":15, "id":13 },
				{ "x":24, "y":16, "id":14 },
				{ "x":24, "y":17, "id":15 },
				{ "x":24, "y":18, "id":16 }
			]
		},
		{
			"name": "Layer 2", 
			"positions": [
				{ "x":3, "y":7, "id":319 },
				{ "x":3, "y":8, "id":319 },
				{ "x":3, "y":9, "id":319 },
				{ "x":3, "y":10, "id":319 },
				{ "x":3, "y":11, "id":319 },
				{ "x":3, "y":12, "id":319 },
				{ "x":3, "y":13, "id":319 },
				{ "x":3, "y":14, "id":319 },
				{ "x":3, "y":15, "id":319 },
				{ "x":4, "y":9, "id":319 },
				{ "x":4, "y":11, "id":319 },
				{ "x":4, "y":12, "id":319 },
				{ "x":4, "y":15, "id":319 },
				{ "x":5, "y":9, "id":319 },
				{ "x":5, "y":15, "id":319 },
				{ "x":6, "y":9, "id":319 },
				{ "x":6, "y":16, "id":319 },
				{ "x":7, "y":6, "id":319 },
				{ "x":7, "y":7, "id":319 },
				{ "x":7, "y":9, "id":319 },
				{ "x":7, "y":16, "id":319 },
				{ "x":7, "y":17, "id":319 },
				{ "x":8, "y":5, "id":319 },
				{ "x":8, "y":6, "id":319 },
				{ "x":8, "y":8, "id":319 },
				{ "x":8, "y":9, "id":319 },
				{ "x":8, "y":17, "id":319 },
				{ "x":9, "y":5, "id":319 },
				{ "x":9, "y":17, "id":319 },
				{ "x":10, "y":5, "id":319 },
				{ "x":10, "y":8, "id":319 },
				{ "x":10, "y":9, "id":319 },
				{ "x":10, "y":10, "id":319 },
				{ "x":10, "y":17, "id":319 },
				{ "x":11, "y":5, "id":319 },
				{ "x":11, "y":8, "id":319 },
				{ "x":11, "y":10, "id":319 },
				{ "x":11, "y":17, "id":319 },
				{ "x":11, "y":18, "id":319 },
				{ "x":12, "y":5, "id":319 },
				{ "x":12, "y":8, "id":319 },
				{ "x":12, "y":9, "id":319 },
				{ "x":12, "y":10, "id":319 },
				{ "x":13, "y":5, "id":319 },
				{ "x":13, "y":17, "id":319 },
				{ "x":13, "y":18, "id":319 },
				{ "x":14, "y":5, "id":319 },
				{ "x":14, "y":17, "id":319 },
				{ "x":15, "y":5, "id":319 },
				{ "x":15, "y":6, "id":319 },
				{ "x":15, "y":7, "id":319 },
				{ "x":15, "y":8, "id":319 },
				{ "x":15, "y":9, "id":319 },
				{ "x":15, "y":11, "id":319 },
				{ "x":15, "y":12, "id":319 },
				{ "x":15, "y":13, "id":319 },
				{ "x":15, "y":14, "id":319 },
				{ "x":15, "y":15, "id":319 },
				{ "x":15, "y":17, "id":319 },
				{ "x":16, "y":5, "id":319 },
				{ "x":16, "y":6, "id":319 },
				{ "x":16, "y":11, "id":319 },
				{ "x":16, "y":14, "id":319 },
				{ "x":16, "y":15, "id":319 },
				{ "x":16, "y":17, "id":319 },
				{ "x":17, "y":5, "id":319 },
				{ "x":17, "y":6, "id":319 },
				{ "x":17, "y":8, "id":319 },
				{ "x":17, "y":11, "id":319 },
				{ "x":17, "y":14, "id":319 },
				{ "x":17, "y":17, "id":319 },
				{ "x":18, "y":5, "id":319 },
				{ "x":18, "y":11, "id":319 },
				{ "x":18, "y":14, "id":319 },
				{ "x":18, "y":17, "id":319 },
				{ "x":19, "y":6, "id":319 },
				{ "x":19, "y":7, "id":319 },
				{ "x":19, "y":11, "id":319 },
				{ "x":19, "y":13, "id":319 },
				{ "x":19, "y":17, "id":319 },
				{ "x":20, "y":6, "id":319 },
				{ "x":20, "y":7, "id":319 },
				{ "x":20, "y":11, "id":319 },
				{ "x":20, "y":14, "id":319 },
				{ "x":20, "y":17, "id":319 },
				{ "x":21, "y":8, "id":319 },
				{ "x":21, "y":9, "id":319 },
				{ "x":21, "y":10, "id":319 },
				{ "x":21, "y":16, "id":319 },
				{ "x":21, "y":17, "id":319 }
			]
		}
	]
}